{"Cleveland": ["Kevin Cutler", "+120", "R", "Toronto", "+2.5", "227.5"], "Toronto": ["Kevin Cutler", "-140", "H", "Cleveland", "-2.5", "227.5"], "Detroit": ["James Capers", "+320", "R", "Houston", "+9.5", "227.5"], "Houston": ["James Capers", "-400", "H", "Detroit", "-9.5", "227.5"], "Indiana": ["Jacyn Goble", "+260", "R", "Milwaukee", "+8.5", "260.5"], "Milwaukee": ["Jacyn Goble", "-325", "H", "Indiana", "-8.5", "260.5"], "Dallas": ["Tyler Ford", "-175", "R", "Utah", "-4.5", "245.5"], "Utah": ["Tyler Ford", "+150", "H", "Dallas", "+4.5", "245.5"], "Portland": ["Sean Wright", "+330", "R", "Phoenix", "+9.5", "227.5"], "Phoenix": ["Sean Wright", "-420", "H", "Portland", "-9.5", "227.5"], "Charlotte": ["David Guthrie", "+850", "R", "Denver", "+15.", "226.5"], "Denver": ["David Guthrie", "-1450", "H", "Charlotte", "-15.", "226.5"], "Miami": ["Ed Malloy", "+230", "R", "LA Clippers", "+7.5", "227.5"], "LA Clippers": ["Ed Malloy", "-285", "H", "Miami", "-7.5", "227.5"]}